sitecustomize/__init__.py
pelicanq_sitecustomize-0.1.0.dist-info/WHEEL
pelicanq_sitecustomize-0.1.0.dist-info/entry_points.txt
pelicanq_sitecustomize-0.1.0.dist-info/METADATA
pelicanq_sitecustomize-0.1.0.dist-info/RECORD
