Metadata-Version: 2.3
Name: pelicanq-sitecustomize
Version: 0.1.0
Summary: For stuff
Author: PelicanQ
Author-email: PelicanQ <77930606+PelicanQ@users.noreply.github.com>
Requires-Python: >=3.12
